qqlib/__init__.py
qqlib/__main__.py
qqlib/qzone.py
qqlib/tea.py
qqlib/hieroglyphy/__init__.py
qqlib/hieroglyphy/data.py
qqlib-1.1.1.dist-info/DESCRIPTION.rst
qqlib-1.1.1.dist-info/METADATA
qqlib-1.1.1.dist-info/RECORD
qqlib-1.1.1.dist-info/WHEEL
qqlib-1.1.1.dist-info/metadata.json
qqlib-1.1.1.dist-info/top_level.txt
